substring_structures/__init__.py
substring_structures/aho_corasick.py
substring_structures/knuth_morris_pratt.py
substring_structures/ukkonens.py
substring_structures-0.0.2.dist-info/METADATA
substring_structures-0.0.2.dist-info/WHEEL
substring_structures-0.0.2.dist-info/licenses/LICENSE
substring_structures-0.0.2.dist-info/RECORD
