Metadata-Version: 2.1
Name: substring_structures
Version: 0.0.2
Summary: Structures for doing substring searches.
Project-URL: Homepage, https://github.com/cmistrata/substring_structures
Author-email: Charlie Mistrata <cmistrata@gmail.com>
License-File: LICENSE
Classifier: License :: OSI Approved :: MIT License
Classifier: Operating System :: OS Independent
Classifier: Programming Language :: Python :: 3
Requires-Python: >=3.10
